{"1000_15": {"NJ": 327, "PR": 950, "FL": 4986, "CA": 1887, "NY": 5085, "VA": 961, "MA": 3928}, "1000_10": {"NJ": 327, "PR": 950, "FL": 4986, "CA": 1887, "NY": 5085, "VA": 961, "MA": 3928}, "1000_6": {"NJ": 327, "PR": 950, "FL": 4986, "CA": 1887, "NY": 5085, "VA": 961, "MA": 3928}, "10_15": {"NJ": 327, "PR": 950, "FL": 4986, "CA": 1887, "NY": 5085, "VA": 961, "MA": 3928}, "1000_16": {"NJ": 327, "PR": 950, "FL": 4986, "CA": 1887, "NY": 5085, "VA": 961, "MA": 3928}, "100_6": {"NJ": 327, "PR": 950, "FL": 4986, "CA": 1887, "NY": 5085, "VA": 961, "MA": 3928}, "1000_17": {"NJ": 327, "PR": 950, "FL": 4986, "CA": 1887, "NY": 5085, "VA": 961, "MA": 3928}, "100_19": {"NJ": 327, "PR": 950, "FL": 4986, "CA": 1887, "NY": 5085, "VA": 961, "MA": 3928}, "100_10": {"NJ": 327, "PR": 950, "FL": 4986, "CA": 1887, "NY": 5085, "VA": 961, "MA": 3928}, "200_11": {"NJ": 327, "PR": 950, "FL": 4986, "CA": 1887, "NY": 5085, "VA": 961, "MA": 3928}, "10_2": {"NJ": 327, "PR": 950, "FL": 4986, "CA": 1887, "NY": 5085, "VA": 961, "MA": 3928}, "500_20": {"NJ": 327, "PR": 950, "FL": 4986, "CA": 1887, "NY": 5085, "VA": 961, "MA": 3928}, "10_14": {"NJ": 327, "PR": 950, "FL": 4986, "CA": 1887, "NY": 5085, "VA": 961, "MA": 3928}, "200_10": {"NJ": 327, "PR": 950, "FL": 4986, "CA": 1887, "NY": 5085, "VA": 961, "MA": 3928}, "10_18": {"NJ": 327, "PR": 950, "FL": 4986, "CA": 1887, "NY": 5085, "VA": 961, "MA": 3928}, "100_11": {"NJ": 327, "PR": 950, "FL": 4986, "CA": 1887, "NY": 5085, "VA": 961, "MA": 3928}, "10_11": {"NJ": 327, "PR": 950, "FL": 4986, "CA": 1887, "NY": 5085, "VA": 961, "MA": 3928}, "500_12": {"NJ": 327, "PR": 950, "FL": 4986, "CA": 1887, "NY": 5085, "VA": 961, "MA": 3928}, "200_7": {"NJ": 327, "PR": 950, "FL": 4986, "CA": 1887, "NY": 5085, "VA": 961, "MA": 3928}, "1000_2": {"NJ": 327, "PR": 950, "FL": 4986, "CA": 1887, "NY": 5085, "VA": 961, "MA": 3928}, "500_18": {"NJ": 327, "PR": 950, "FL": 4986, "CA": 1887, "NY": 5085, "VA": 961, "MA": 3928}, "10_17": {"NJ": 327, "PR": 950, "FL": 4986, "CA": 1887, "NY": 5085, "VA": 961, "MA": 3928}, "500_9": {"NJ": 327, "PR": 950, "FL": 4986, "CA": 1887, "NY": 5085, "VA": 961, "MA": 3928}, "1000_19": {"NJ": 327, "PR": 950, "FL": 4986, "CA": 1887, "NY": 5085, "VA": 961, "MA": 3928}, "200_4": {"NJ": 327, "PR": 950, "FL": 4986, "CA": 1887, "NY": 5085, "VA": 961, "MA": 3928}, "500_15": {"NJ": 327, "PR": 950, "FL": 4986, "CA": 1887, "NY": 5085, "VA": 961, "MA": 3928}, "200_6": {"NJ": 327, "PR": 950, "FL": 4986, "CA": 1887, "NY": 5085, "VA": 961, "MA": 3928}, "10_12": {"NJ": 327, "PR": 950, "FL": 4986, "CA": 1887, "NY": 5085, "VA": 961, "MA": 3928}, "100_12": {"NJ": 327, "PR": 950, "FL": 4986, "CA": 1887, "NY": 5085, "VA": 961, "MA": 3928}, "200_8": {"NJ": 327, "PR": 950, "FL": 4986, "CA": 1887, "NY": 5085, "VA": 961, "MA": 3928}, "1000_20": {"NJ": 327, "PR": 950, "FL": 4986, "CA": 1887, "NY": 5085, "VA": 961, "MA": 3928}, "500_16": {"NJ": 327, "PR": 950, "FL": 4986, "CA": 1887, "NY": 5085, "VA": 961, "MA": 3928}, "100_14": {"NJ": 327, "PR": 950, "FL": 4986, "CA": 1887, "NY": 5085, "VA": 961, "MA": 3928}, "200_2": {"NJ": 327, "PR": 950, "FL": 4986, "CA": 1887, "NY": 5085, "VA": 961, "MA": 3928}, "1000_7": {"NJ": 327, "PR": 950, "FL": 4986, "CA": 1887, "NY": 5085, "VA": 961, "MA": 3928}, "500_19": {"NJ": 327, "PR": 950, "FL": 4986, "CA": 1887, "NY": 5085, "VA": 961, "MA": 3928}, "200_5": {"NJ": 327, "PR": 950, "FL": 4986, "CA": 1887, "NY": 5085, "VA": 961, "MA": 3928}, "10_19": {"NJ": 327, "PR": 950, "FL": 4986, "CA": 1887, "NY": 5085, "VA": 961, "MA": 3928}, "100_2": {"NJ": 327, "PR": 950, "FL": 4986, "CA": 1887, "NY": 5085, "VA": 961, "MA": 3928}, "200_19": {"NJ": 327, "PR": 950, "FL": 4986, "CA": 1887, "NY": 5085, "VA": 961, "MA": 3928}, "10_20": {"NJ": 327, "PR": 950, "FL": 4986, "CA": 1887, "NY": 5085, "VA": 961, "MA": 3928}, "500_11": {"NJ": 327, "PR": 950, "FL": 4986, "CA": 1887, "NY": 5085, "VA": 961, "MA": 3928}, "10_5": {"NJ": 327, "PR": 950, "FL": 4986, "CA": 1887, "NY": 5085, "VA": 961, "MA": 3928}, "200_21": {"NJ": 327, "PR": 950, "FL": 4986, "CA": 1887, "NY": 5085, "VA": 961, "MA": 3928}, "10_9": {"NJ": 327, "PR": 950, "FL": 4986, "CA": 1887, "NY": 5085, "VA": 961, "MA": 3928}, "500_6": {"NJ": 327, "PR": 950, "FL": 4986, "CA": 1887, "NY": 5085, "VA": 961, "MA": 3928}, "500_5": {"NJ": 327, "PR": 950, "FL": 4986, "CA": 1887, "NY": 5085, "VA": 961, "MA": 3928}, "100_5": {"NJ": 327, "PR": 950, "FL": 4986, "CA": 1887, "NY": 5085, "VA": 961, "MA": 3928}, "100_4": {"NJ": 327, "PR": 950, "FL": 4986, "CA": 1887, "NY": 5085, "VA": 961, "MA": 3928}, "500_7": {"NJ": 327, "PR": 950, "FL": 4986, "CA": 1887, "NY": 5085, "VA": 961, "MA": 3928}, "200_18": {"NJ": 327, "PR": 950, "FL": 4986, "CA": 1887, "NY": 5085, "VA": 961, "MA": 3928}, "200_16": {"NJ": 327, "PR": 950, "FL": 4986, "CA": 1887, "NY": 5085, "VA": 961, "MA": 3928}, "500_21": {"NJ": 327, "PR": 950, "FL": 4986, "CA": 1887, "NY": 5085, "VA": 961, "MA": 3928}, "10_4": {"NJ": 327, "PR": 950, "FL": 4986, "CA": 1887, "NY": 5085, "VA": 961, "MA": 3928}, "200_13": {"NJ": 327, "PR": 950, "FL": 4986, "CA": 1887, "NY": 5085, "VA": 961, "MA": 3928}, "1000_8": {"NJ": 327, "PR": 950, "FL": 4986, "CA": 1887, "NY": 5085, "VA": 961, "MA": 3928}, "500_10": {"NJ": 327, "PR": 950, "FL": 4986, "CA": 1887, "NY": 5085, "VA": 961, "MA": 3928}, "10_8": {"NJ": 327, "PR": 950, "FL": 4986, "CA": 1887, "NY": 5085, "VA": 961, "MA": 3928}, "10_16": {"NJ": 327, "PR": 950, "FL": 4986, "CA": 1887, "NY": 5085, "VA": 961, "MA": 3928}, "200_3": {"NJ": 327, "PR": 950, "FL": 4986, "CA": 1887, "NY": 5085, "VA": 961, "MA": 3928}, "500_17": {"NJ": 327, "PR": 950, "FL": 4986, "CA": 1887, "NY": 5085, "VA": 961, "MA": 3928}, "200_14": {"NJ": 327, "PR": 950, "FL": 4986, "CA": 1887, "NY": 5085, "VA": 961, "MA": 3928}, "100_18": {"NJ": 327, "PR": 950, "FL": 4986, "CA": 1887, "NY": 5085, "VA": 961, "MA": 3928}, "10_13": {"NJ": 327, "PR": 950, "FL": 4986, "CA": 1887, "NY": 5085, "VA": 961, "MA": 3928}, "10_3": {"NJ": 327, "PR": 950, "FL": 4986, "CA": 1887, "NY": 5085, "VA": 961, "MA": 3928}, "200_9": {"NJ": 327, "PR": 950, "FL": 4986, "CA": 1887, "NY": 5085, "VA": 961, "MA": 3928}, "500_3": {"NJ": 327, "PR": 950, "FL": 4986, "CA": 1887, "NY": 5085, "VA": 961, "MA": 3928}, "500_4": {"NJ": 327, "PR": 950, "FL": 4986, "CA": 1887, "NY": 5085, "VA": 961, "MA": 3928}, "500_8": {"NJ": 327, "PR": 950, "FL": 4986, "CA": 1887, "NY": 5085, "VA": 961, "MA": 3928}, "1_1": {"NJ": 327, "PR": 950, "FL": 4986, "CA": 1887, "NY": 5085, "VA": 961, "MA": 3928}, "200_15": {"NJ": 327, "PR": 950, "FL": 4986, "CA": 1887, "NY": 5085, "VA": 961, "MA": 3928}, "10_10": {"NJ": 327, "PR": 950, "FL": 4986, "CA": 1887, "NY": 5085, "VA": 961, "MA": 3928}, "1000_21": {"NJ": 327, "PR": 950, "FL": 4986, "CA": 1887, "NY": 5085, "VA": 961, "MA": 3928}, "100_16": {"NJ": 327, "PR": 950, "FL": 4986, "CA": 1887, "NY": 5085, "VA": 961, "MA": 3928}, "100_3": {"NJ": 327, "PR": 950, "FL": 4986, "CA": 1887, "NY": 5085, "VA": 961, "MA": 3928}, "10_6": {"NJ": 327, "PR": 950, "FL": 4986, "CA": 1887, "NY": 5085, "VA": 961, "MA": 3928}, "200_20": {"NJ": 327, "PR": 950, "FL": 4986, "CA": 1887, "NY": 5085, "VA": 961, "MA": 3928}, "1000_11": {"NJ": 327, "PR": 950, "FL": 4986, "CA": 1887, "NY": 5085, "VA": 961, "MA": 3928}, "500_13": {"NJ": 327, "PR": 950, "FL": 4986, "CA": 1887, "NY": 5085, "VA": 961, "MA": 3928}, "100_8": {"NJ": 327, "PR": 950, "FL": 4986, "CA": 1887, "NY": 5085, "VA": 961, "MA": 3928}, "100_7": {"NJ": 327, "PR": 950, "FL": 4986, "CA": 1887, "NY": 5085, "VA": 961, "MA": 3928}, "100_9": {"NJ": 327, "PR": 950, "FL": 4986, "CA": 1887, "NY": 5085, "VA": 961, "MA": 3928}, "500_2": {"NJ": 327, "PR": 950, "FL": 4986, "CA": 1887, "NY": 5085, "VA": 961, "MA": 3928}, "1000_13": {"NJ": 327, "PR": 950, "FL": 4986, "CA": 1887, "NY": 5085, "VA": 961, "MA": 3928}, "1_0": {"NJ": 327, "PR": 950, "FL": 4986, "CA": 1887, "NY": 5085, "VA": 961, "MA": 3928}, "100_21": {"NJ": 327, "PR": 950, "FL": 4986, "CA": 1887, "NY": 5085, "VA": 961, "MA": 3928}, "1000_3": {"NJ": 327, "PR": 950, "FL": 4986, "CA": 1887, "NY": 5085, "VA": 961, "MA": 3928}, "500_14": {"NJ": 327, "PR": 950, "FL": 4986, "CA": 1887, "NY": 5085, "VA": 961, "MA": 3928}, "10_21": {"NJ": 327, "PR": 950, "FL": 4986, "CA": 1887, "NY": 5085, "VA": 961, "MA": 3928}, "100_17": {"NJ": 327, "PR": 950, "FL": 4986, "CA": 1887, "NY": 5085, "VA": 961, "MA": 3928}, "1000_5": {"NJ": 327, "PR": 950, "FL": 4986, "CA": 1887, "NY": 5085, "VA": 961, "MA": 3928}, "1000_12": {"NJ": 327, "PR": 950, "FL": 4986, "CA": 1887, "NY": 5085, "VA": 961, "MA": 3928}, "200_17": {"NJ": 327, "PR": 950, "FL": 4986, "CA": 1887, "NY": 5085, "VA": 961, "MA": 3928}, "1000_4": {"NJ": 327, "PR": 950, "FL": 4986, "CA": 1887, "NY": 5085, "VA": 961, "MA": 3928}, "200_12": {"NJ": 327, "PR": 950, "FL": 4986, "CA": 1887, "NY": 5085, "VA": 961, "MA": 3928}, "100_13": {"NJ": 327, "PR": 950, "FL": 4986, "CA": 1887, "NY": 5085, "VA": 961, "MA": 3928}, "1000_9": {"NJ": 327, "PR": 950, "FL": 4986, "CA": 1887, "NY": 5085, "VA": 961, "MA": 3928}, "100_15": {"NJ": 327, "PR": 950, "FL": 4986, "CA": 1887, "NY": 5085, "VA": 961, "MA": 3928}, "1000_18": {"NJ": 327, "PR": 950, "FL": 4986, "CA": 1887, "NY": 5085, "VA": 961, "MA": 3928}, "100_20": {"NJ": 327, "PR": 950, "FL": 4986, "CA": 1887, "NY": 5085, "VA": 961, "MA": 3928}, "10_7": {"NJ": 327, "PR": 950, "FL": 4986, "CA": 1887, "NY": 5085, "VA": 961, "MA": 3928}, "1000_14": {"NJ": 327, "PR": 950, "FL": 4986, "CA": 1887, "NY": 5085, "VA": 961, "MA": 3928}}